pyrcn/__init__.py
pyrcn/_version.py
pyrcn/autoencoder/__init__.py
pyrcn/autoencoder/_ae.py
pyrcn/base/__init__.py
pyrcn/base/_activations.py
pyrcn/base/_base.py
pyrcn/base/blocks/__init__.py
pyrcn/base/blocks/_input_to_node.py
pyrcn/base/blocks/_node_to_node.py
pyrcn/datasets/__init__.py
pyrcn/datasets/_base.py
pyrcn/datasets/_maps_piano_dataset.py
pyrcn/datasets/_ptdb_tug.py
pyrcn/echo_state_network/__init__.py
pyrcn/echo_state_network/_esn.py
pyrcn/extreme_learning_machine/__init__.py
pyrcn/extreme_learning_machine/_elm.py
pyrcn/linear_model/__init__.py
pyrcn/linear_model/_incremental_regression.py
pyrcn/metrics/__init__.py
pyrcn/metrics/_classification.py
pyrcn/metrics/_regression.py
pyrcn/model_selection/__init__.py
pyrcn/model_selection/_search.py
pyrcn/postprocessing/__init__.py
pyrcn/postprocessing/_normal_distribution.py
pyrcn/preprocessing/__init__.py
pyrcn/preprocessing/_coates.py
pyrcn/projection/__init__.py
pyrcn/projection/_value_projection.py
pyrcn/util/__init__.py
pyrcn/util/_feature_extractor.py
pyrcn/util/_util.py
PyRCN-0.0.18.dist-info/LICENSE
PyRCN-0.0.18.dist-info/METADATA
PyRCN-0.0.18.dist-info/WHEEL
PyRCN-0.0.18.dist-info/top_level.txt
PyRCN-0.0.18.dist-info/RECORD
