Metadata-Version: 2.1
Name: PyRCN
Version: 0.0.18
Summary: A scikit-learn-compatible framework for Reservoir Computing in Python
Home-page: https://github.com/TUD-STKS/PyRCN
Author: Peter Steiner
Author-email: peter.steiner@pyrcn.net
Project-URL: Documentation, https://pyrcn.readthedocs.io/
Project-URL: Funding, https://pyrcn.net/
Project-URL: Source, https://github.com/TUD-STKS/PyRCN/
Project-URL: Bug Tracker, https://github.com/TUD-STKS/PyRCN/issues
Classifier: Programming Language :: Python :: 3
Classifier: Development Status :: 2 - Pre-Alpha
Classifier: License :: OSI Approved :: BSD License
Classifier: Operating System :: OS Independent
Classifier: Intended Audience :: Science/Research
Requires-Python: >=3.9
License-File: LICENSE
